modularbuildingpy/__init__.py
modularbuildingpy/data/SteelSections_W_HSS.xlsx
modularbuildingpy/data/aisc-shapes-database-v15.0.xlsx
modularbuildingpy/data/aisc-shapes-database-v16.0.xlsx
modularbuildingpy/utils/__init__.py
modularbuildingpy/utils/helper.py
modularbuildingpy-0.2.5.2.dist-info/LICENSE
modularbuildingpy-0.2.5.2.dist-info/METADATA
modularbuildingpy-0.2.5.2.dist-info/WHEEL
modularbuildingpy-0.2.5.2.dist-info/top_level.txt
modularbuildingpy-0.2.5.2.dist-info/RECORD
