Metadata-Version: 2.1
Name: modularbuildingpy
Version: 0.2.5.2
Summary: A python module to create linear or nonlinear numerical models for volumetric modular steel buildings using the finite element method (OpenSeesPy).
Home-page: https://github.com/mbbatukan/ModularBuildingPy.git
Author: Mehmet Baris Batukan
Author-email: mbbatu@hotmail.com
Classifier: Development Status :: 3 - Alpha
Classifier: License :: OSI Approved :: MIT License
Classifier: Programming Language :: Python :: 3.11
License-File: LICENSE
Requires-Dist: numpy ==1.25.2
Requires-Dist: pandas ==2.1.0
Requires-Dist: matplotlib ==3.7.3
Requires-Dist: openseespy ==3.5.1.12
Requires-Dist: ipyparallel ==8.6.1
Requires-Dist: openpyxl ==3.1.2
Requires-Dist: pymetis ==2023.1.1
Requires-Dist: requests ==2.31.0
Requires-Dist: scipy ==1.11.2
Requires-Dist: shapely ==2.0.2
